README.rst
setup.py
sass_cli/__init__.py
sass_cli/main.py
sass_cli.egg-info/PKG-INFO
sass_cli.egg-info/SOURCES.txt
sass_cli.egg-info/dependency_links.txt
sass_cli.egg-info/entry_points.txt
sass_cli.egg-info/requires.txt
sass_cli.egg-info/top_level.txt