Metadata-Version: 1.1
Name: sass-cli
Version: 0.0.3
Summary: CLI for SASS compliation
Home-page: http://bmcorser.github.com/sass-cli
Author: bmcorser
Author-email: bmcorser@gmail.com
License: UNKNOWN
Platform: UNKNOWN
Classifier: Programming Language :: Python :: 3 :: Only
